[
	{
		"name": "chairmanz-resort",
		"slug": "bangalore-drink-deals/chairmans-jade-resort-devanahalli.html",
		"method": "GET"
	},
	{
		"name": "woodstock-indira-nagar",
		"slug": "bangalore-drink-deals/woodstok-indira-nagar.html",
		"method": "GET"
	},
	{
		"name": "via-milano",
		"slug": "bangalore-drink-deals/via-milano-italian-restaurant-lounge-koramangala.html",
		"method": "GET"
	},
	{
		"name": "barleyz",
		"slug": "bangalore-drink-deals/barleyz-the-brew-house-koramangala.html",
		"method": "GET"
	},
	{
		"name": "platter-banashankari",
		"slug": "bangalore-drink-deals/the-platter-restaurant-lounge-banashankari.html",
		"method": "GET"
	},
	{
		"name": "index",
		"slug": "index.html",
		"method": "GET"
	},
	{
		"name": "business",
		"slug": "business.html",
		"method": "GET"
	},
	{
		"name": "careers",
		"slug": "careers.html",
		"method": "GET"
	},
	{
		"name": "about",
		"slug": "about.html",
		"method": "GET"
	},
	{
		"name": "contact",
		"slug": "contact.html",
		"method": "GET"
	},
	{
		"name": "deal-showcase",
		"slug": "deal-showcase.html",
		"method": "GET"
	},
	{
		"name": "careers/js-ninja",
		"slug": "careers/javascript-ninja.html",
		"method": "GET"
	},
	{
		"name": "careers/web-developer",
		"slug": "careers/web-developer.html",
		"method": "GET"
	},
	{
		"name": "careers/web-graphic-designer",
		"slug": "careers/web-graphic-designer.html",
		"method": "GET"
	},
	{
		"name": "careers/sales-manager",
		"slug": "careers/sales-manager.html",
		"method": "GET"
	},
	{
		"name": "careers/inside-sales",
		"slug": "careers/inside-sales.html",
		"method": "GET"
	},
	{
		"name": "peacock",
		"slug": "bangalore-drink-deals/peacock-indira-nagar.html",
		"method": "GET"
	},
	{
		"name": "careers/marketing",
		"slug": "careers/marketing.html",
		"method": "GET"
	},
	{
		"name": "doff-the-pub-n-lounge",
		"slug": "bangalore-drink-deals/doff-the-pub-and-lounge-indira-nagar.html",
		"method": "GET"
	}
]